LICENSE
MANIFEST.in
README.rst
requirements.txt
setup.py
tox.ini
docs/Makefile
docs/conf.py
docs/index.rst
docs/make.bat
fodeint/__init__.py
fodeint/fodeint.py
fodeint.egg-info/PKG-INFO
fodeint.egg-info/SOURCES.txt
fodeint.egg-info/dependency_links.txt
fodeint.egg-info/not-zip-safe
fodeint.egg-info/requires.txt
fodeint.egg-info/top_level.txt