Metadata-Version: 1.1
Name: fodeint
Version: 0.1.0
Summary: Numerical integration of fractional ordinary differential equations (FODE)
Home-page: http://github.com/mattja/fodeint/
Author: Matthew J. Aburn
Author-email: mattja6@gmail.com
License: GPLv3+
Keywords: fractional,differential equations,FDE,FODE
Platform: any
Classifier: Programming Language :: Python
Classifier: Development Status :: 2 - Pre-Alpha
Classifier: Intended Audience :: Science/Research
Classifier: License :: OSI Approved :: GNU General Public License (GPL)
Classifier: Operating System :: OS Independent
Classifier: Topic :: Scientific/Engineering
